md0network/dist/md0network-0.0.4.tar.gz
md0network/network.py
md0network/pyproject.toml
md0network/wokrflow.yml
md0network-0.0.4.dist-info/METADATA
md0network-0.0.4.dist-info/WHEEL
md0network-0.0.4.dist-info/RECORD
