Metadata-Version: 2.1
Name: MD0network
Version: 0.0.4
Summary: A tool to make sending and reciving messages on a network easier
Home-page: https://www.lambda-tech.org/
License: MIT
Keywords: python,module,requests
Author: MD0
Author-email: Midnightdodger0@gmail.com
Requires-Python: >=3.8,<4.0
Classifier: Intended Audience :: Developers
Classifier: License :: OSI Approved :: MIT License
Classifier: Programming Language :: Python :: 3
Classifier: Programming Language :: Python :: 3.8
Classifier: Programming Language :: Python :: 3.9
Classifier: Programming Language :: Python :: 3.10
Classifier: Programming Language :: Python :: 3.11
Classifier: Programming Language :: Python :: 3.12
Classifier: Programming Language :: Python :: 3.13
Requires-Dist: requests (>=2.28.0,<3.0.0)
Project-URL: Repository, https://github.com/midnightdodger/MD0network
